.gitignore
ChangeLog
LICENSE.txt
MANIFEST
README.md
setup.cfg
setup.py
./qpack/_qpack.c
.github/workflows/ci.yml
qpack/.gitignore
qpack/__init__.py
qpack/_qpack.c
qpack/fallback.py
qpack.egg-info/PKG-INFO
qpack.egg-info/SOURCES.txt
qpack.egg-info/dependency_links.txt
qpack.egg-info/top_level.txt
test/qpack_test.py