Metadata-Version: 1.1
Name: qpack
Version: 0.0.21
Summary: QPack (de)serializer
Home-page: https://github.com/cesbit/qpack
Author: Jeroen van der Heijden
Author-email: jeroen@cesbit.com
License: UNKNOWN
Download-URL: https://github.com/cesbit/qpack/tarball/0.0.21
Keywords: serializer,deserializer
Platform: UNKNOWN
Classifier: Development Status :: 4 - Beta
Classifier: Environment :: Other Environment
Classifier: Intended Audience :: Developers
Classifier: License :: OSI Approved :: MIT License
Classifier: Operating System :: OS Independent
Classifier: Programming Language :: Python :: 2
Classifier: Programming Language :: Python :: 3
Classifier: Topic :: Software Development
